snipsync/__init__.py
snipsync/environment.py
snipsync/lexer.py
snipsync/main.py
snipsync/position.py
snipsync/text.py
snipsync/ultisnip.py
snipsync/xml_snippet.py
tests/__init__.py
tests/conftest.py
tests/test_cli.py
tests/test_environment.py
tests/test_io.py
tests/test_main.py
tests/test_tokenize.py
tests/test_ultisnip.py
snipsync-1.0.3.dist-info/LICENSE
snipsync-1.0.3.dist-info/METADATA
snipsync-1.0.3.dist-info/WHEEL
snipsync-1.0.3.dist-info/entry_points.txt
snipsync-1.0.3.dist-info/top_level.txt
snipsync-1.0.3.dist-info/RECORD
