Metadata-Version: 2.1
Name: snipsync
Version: 1.0.3
Summary: Syncs Ultisnips snippets to Intelij
Home-page: https://github.com/sysid/snipsync
Author: sysid
Author-email: sysid@gmx.de
License: UNKNOWN
Platform: UNKNOWN
Classifier: Programming Language :: Python :: 3
Classifier: License :: OSI Approved :: BSD License
Classifier: Operating System :: OS Independent
Requires-Python: >=3.9
License-File: LICENSE
Requires-Dist: typer
Requires-Dist: pydantic
